<?xml version="1.0"?>
<!--
/**
 * CNTechnoLabs
 * Copyright (C) 2023 CNTechnoLabs 
 *
 * @category  CNTechnoLabs
 * @package   CNTechnoLabs_ScrollTop
 * @copyright Copyright (c) 2023 CNTechnoLabs
 * @license   http://opensource.org/licenses/gpl-3.0.html GNU General Public License,version 3 (GPL-3.0)
 * @author    CNTechnoLabs
 */
-->

<page xmlns:xsi="http://www.w3.org/2001/XMLSchema-instance" xsi:noNamespaceSchemaLocation="urn:magento:framework:View/Layout/etc/page_configuration.xsd">
    <head>
        <css src="CNTechnoLabs_ScrollTop::css/scrolltop.css"/>
        <script src="CNTechnoLabs_ScrollTop::js/scrolltop.js"/>
    </head>

    <body>
        <referenceContainer name="footer-container">
            <block class="CNTechnoLabs\ScrollTop\Block\ScrollTop" name="cnt.scrolltop" template="CNTechnoLabs_ScrollTop::scrolltop.phtml"/>
        </referenceContainer>
    </body>
</page>
